tab2dict/__init__.py
tab2dict/tab_dict.py
tab2dict-0.0.4.dist-info/LICENSE.txt
tab2dict-0.0.4.dist-info/METADATA
tab2dict-0.0.4.dist-info/WHEEL
tab2dict-0.0.4.dist-info/top_level.txt
tab2dict-0.0.4.dist-info/RECORD
